retrievers/__init__.py
retrievers-0.1.0.dist-info/LICENSE
retrievers-0.1.0.dist-info/WHEEL
retrievers-0.1.0.dist-info/METADATA
retrievers-0.1.0.dist-info/RECORD
